enot_autodl-3.7.2.dist-info/RECORD
enot_autodl-3.7.2.dist-info/LICENSE
enot_autodl-3.7.2.dist-info/METADATA
enot_autodl-3.7.2.dist-info/top_level.txt
enot_autodl-3.7.2.dist-info/WHEEL
enot/__init__.py
enot/py.typed
enot/optimization/gt_baseline_optimizer.pyi
enot/optimization/__init__.py
enot/optimization/__init__.pyi
enot/optimization/gt_baseline_optimizer.cpython-39-x86_64-linux-gnu.so
enot/logging/logging.cpython-39-x86_64-linux-gnu.so
enot/logging/__init__.py
enot/logging/logging.pyi
enot/logging/__init__.pyi
enot/quantization/fake_quantized_model.cpython-39-x86_64-linux-gnu.so
enot/quantization/stm_fake_quantized_model.cpython-39-x86_64-linux-gnu.so
enot/quantization/ov_fake_quantized_model.pyi
enot/quantization/__init__.py
enot/quantization/trt_fake_quantized_model.pyi
enot/quantization/trt_fake_quantized_model.cpython-39-x86_64-linux-gnu.so
enot/quantization/quant_distillation_layer.cpython-39-x86_64-linux-gnu.so
enot/quantization/stm_fake_quantized_model.pyi
enot/quantization/ov_fake_quantized_model.cpython-39-x86_64-linux-gnu.so
enot/quantization/fake_quantized_model.pyi
enot/quantization/qnn/adaptive_avg_pool2d.cpython-39-x86_64-linux-gnu.so
enot/quantization/qnn/se_block.cpython-39-x86_64-linux-gnu.so
enot/quantization/qnn/__init__.py
enot/quantization/qnn/conv.cpython-39-x86_64-linux-gnu.so
enot/quantization/qnn/add.cpython-39-x86_64-linux-gnu.so
enot/quantization/qnn/flatten.cpython-39-x86_64-linux-gnu.so
enot/quantization/qnn/conv_norm_silu.cpython-39-x86_64-linux-gnu.so
enot/quantization/qnn/linear.cpython-39-x86_64-linux-gnu.so
enot/quantization/qnn/matmul.cpython-39-x86_64-linux-gnu.so
enot/quantization/qnn/quantized_layer.cpython-39-x86_64-linux-gnu.so
enot/quantization/qnn/weight_quantization_module.cpython-39-x86_64-linux-gnu.so
enot/quantization/qnn/fake_quantization/fake_quantization_builder.cpython-39-x86_64-linux-gnu.so
enot/quantization/qnn/fake_quantization/fake_quantization.cpython-39-x86_64-linux-gnu.so
enot/quantization/qnn/fake_quantization/__init__.py
enot/quantization/qnn/fake_quantization/fake_quantization_factory.cpython-39-x86_64-linux-gnu.so
