Metadata-Version: 2.1
Name: enot-autodl
Version: 3.7.2
Summary: AutoDL framework for neural network compression & acceleration
Author-email: ENOT LLC <enot@enot.ai>
License: ENOT License v1.0
Project-URL: homepage, https://enot.ai
Project-URL: documentation, https://enot-autodl.rtd.enot.ai/en/stable
Keywords: AI,Neural architecture search
Classifier: Development Status :: 5 - Production/Stable
Classifier: License :: Other/Proprietary License
Classifier: Programming Language :: Python
Classifier: Programming Language :: Python :: 3.8
Classifier: Programming Language :: Python :: 3.9
Classifier: Programming Language :: Python :: 3.10
Classifier: Programming Language :: Python :: 3 :: Only
Classifier: Topic :: Scientific/Engineering
Classifier: Topic :: Scientific/Engineering :: Artificial Intelligence
Classifier: Topic :: Software Development
Classifier: Topic :: Software Development :: Libraries
Classifier: Topic :: Software Development :: Libraries :: Python Modules
Requires-Python: >=3.8
License-File: LICENSE
Requires-Dist: torch <2.4.0,>=1.10.0
Requires-Dist: torchvision
Requires-Dist: numpy
Requires-Dist: networkx
Requires-Dist: pulp ==2.4
Requires-Dist: tabulate
Requires-Dist: tqdm
Requires-Dist: botorch <0.8.0,>=0.4.0
Requires-Dist: optuna
Requires-Dist: onnx2torch
Requires-Dist: dill >=0.3.1
Requires-Dist: typing-extensions
Provides-Extra: dev
Requires-Dist: black ; extra == 'dev'
Requires-Dist: black[jupyter] ; extra == 'dev'
Requires-Dist: enot-prunable-modules[dev] ; extra == 'dev'
Requires-Dist: fvcore ; extra == 'dev'
Requires-Dist: nbmake ; extra == 'dev'
Requires-Dist: pytest <8.1 ; extra == 'dev'
Requires-Dist: pre-commit ; extra == 'dev'
Requires-Dist: tensorboard ; extra == 'dev'
Requires-Dist: pyyaml ; extra == 'dev'
Requires-Dist: onnx ; extra == 'dev'
Requires-Dist: onnxsim ; extra == 'dev'
